duck_plot/__init__.py
duck_plot/__main__.py
duck_plot/cli.py
duck_plot-0.12.dist-info/LICENSE
duck_plot-0.12.dist-info/METADATA
duck_plot-0.12.dist-info/WHEEL
duck_plot-0.12.dist-info/entry_points.txt
duck_plot-0.12.dist-info/top_level.txt
duck_plot-0.12.dist-info/RECORD
