Metadata-Version: 2.2
Name: duck-plot
Version: 0.12
Summary: Plot the output of duckdb query
Author: Lyubomir Georgiev
License: Apache-2.0
Project-URL: Homepage, https://github.com/lvg77/duck-plot
Project-URL: Changelog, https://github.com/lvg77/duck-plot/releases
Project-URL: Issues, https://github.com/lvg77/duck-plot/issues
Project-URL: CI, https://github.com/lvg77/duck-plot/actions
Classifier: License :: OSI Approved :: Apache Software License
Requires-Python: >=3.10
License-File: LICENSE
Requires-Dist: altair>=5.4.1
Requires-Dist: duckdb>=1.1.3
Requires-Dist: pandas
Requires-Dist: typer
Provides-Extra: test
Requires-Dist: pytest; extra == "test"
